librespot/__init__.py
librespot/cache.py
librespot/core.py
librespot/crypto.py
librespot/dealer.py
librespot/mercury.py
librespot/metadata.py
librespot/oauth.py
librespot/structure.py
librespot/util.py
librespot/zeroconf.py
librespot/audio/__init__.py
librespot/audio/decoders.py
librespot/audio/decrypt.py
librespot/audio/format.py
librespot/audio/storage.py
librespot/proto/Authentication_pb2.py
librespot/proto/CanvazMeta_pb2.py
librespot/proto/Canvaz_pb2.py
librespot/proto/ClientToken_pb2.py
librespot/proto/Connect_pb2.py
librespot/proto/Connectivity_pb2.py
librespot/proto/ContextPage_pb2.py
librespot/proto/ContextPlayerOptions_pb2.py
librespot/proto/ContextTrack_pb2.py
librespot/proto/Context_pb2.py
librespot/proto/EntityExtensionData_pb2.py
librespot/proto/ExplicitContentPubsub_pb2.py
librespot/proto/ExtendedMetadata_pb2.py
librespot/proto/ExtensionKind_pb2.py
librespot/proto/Keyexchange_pb2.py
librespot/proto/Mercury_pb2.py
librespot/proto/Metadata_pb2.py
librespot/proto/PlayOrigin_pb2.py
librespot/proto/Playback_pb2.py
librespot/proto/Player_pb2.py
librespot/proto/Playlist4External_pb2.py
librespot/proto/PlaylistAnnotate3_pb2.py
librespot/proto/Pubsub_pb2.py
librespot/proto/Queue_pb2.py
librespot/proto/Restrictions_pb2.py
librespot/proto/Session_pb2.py
librespot/proto/StorageResolve_pb2.py
librespot/proto/TransferState_pb2.py
librespot/proto/__init__.py
librespot/proto/spotify/__init__.py
librespot/proto/spotify/login5/__init__.py
librespot/proto/spotify/login5/v3/ClientInfo_pb2.py
librespot/proto/spotify/login5/v3/Login5_pb2.py
librespot/proto/spotify/login5/v3/UserInfo_pb2.py
librespot/proto/spotify/login5/v3/__init__.py
librespot/proto/spotify/login5/v3/challenges/Code_pb2.py
librespot/proto/spotify/login5/v3/challenges/Hashcash_pb2.py
librespot/proto/spotify/login5/v3/challenges/__init__.py
librespot/proto/spotify/login5/v3/credentials/Credentials_pb2.py
librespot/proto/spotify/login5/v3/credentials/__init__.py
librespot-0.0.10.dist-info/LICENSE.txt
librespot-0.0.10.dist-info/METADATA
librespot-0.0.10.dist-info/WHEEL
librespot-0.0.10.dist-info/top_level.txt
librespot-0.0.10.dist-info/RECORD
