Metadata-Version: 2.1
Name: librespot
Version: 0.0.10
Summary: Open Source Spotify Client
Home-page: https://github.com/kokarare1212/librespot-python
Author: kokarare1212
License: Apache-2.0
Classifier: Development Status :: 1 - Planning
Classifier: License :: OSI Approved :: Apache Software License
Classifier: Topic :: Multimedia :: Sound/Audio
License-File: LICENSE.txt
Requires-Dist: defusedxml>=0.7.1
Requires-Dist: protobuf==3.20.1
Requires-Dist: pycryptodomex>=3.22.0
Requires-Dist: pyogg>=0.6.14a.1
Requires-Dist: requests>=2.32.3
Requires-Dist: websocket-client>=1.8.0
Requires-Dist: zeroconf>=0.146.4
